wifi/__init__.py
wifi/api/__init__.py
wifi/api/api.py
wifi/connections/clickhouse.py
wifi/connections/connections.py
wifi/connections/elastic.py
wifi/core/__init__.py
wifi/core/core.py
wifi/core/delta_q.py
wifi/core/enforce.py
wifi/core/expert.py
wifi/core/intel.py
wifi/data/arch/axtract_sender.py
wifi/data/arch/dispatcher.py
wifi/data/arch/f.py
wifi/data/arch/kafka/d2
wifi/data/arch/kafka/d3
wifi/data/arch/kafka/data
wifi/data/arch/kafka/kafka.py
wifi/data/arch/olddisp.py
wifi/data/arch/sample_data/FG824CD.py
wifi/data/arch/sample_data/H500s.py
wifi/data/arch/sample_data/vf.py
wifi/data/arch/sample_data/vf2.py.o
wifi/data/arch/sample_data/vvv
wifi/data/arch/socketclient.py
wifi/functions.py
wifi/helper_scripts/upgrade_flows.py
wifi/js/nodered/flows_lib/default_flows.json
wifi/operations/inject/Boot.json
wifi/operations/inject/BulkData..json
wifi/operations/inject/Connect.json
wifi/operations/inject/Ext.IP.json
wifi/operations/inject/FullScanBulk.json
wifi/operations/inject/HealthCheck.json
wifi/operations/inject/Hosts.json
wifi/operations/inject/Jointelli_S22_USP.json
wifi/operations/inject/LSGetJoinTelli.json
wifi/operations/inject/Light Scan.json
wifi/operations/inject/LightScan..json
wifi/operations/inject/LocalAgent.Subscription..json
wifi/operations/inject/No WiFi.json
wifi/operations/inject/README.md
wifi/operations/inject/Reboot.json
wifi/operations/inject/Set.json
wifi/operations/inject/Simulate Mesh JSON full.json
wifi/operations/inject/Simulate Mesh JSON.json
wifi/operations/inject/Simulate Mesh JSON2.json
wifi/operations/inject/SupportedDM.json
wifi/operations/inject/TiggerFullScan AVM.json
wifi/operations/inject/TiggerSpeedtest.json
wifi/operations/inject/_.Device. full .json
wifi/operations/inject/_.DeviceInfo. level 2.json
wifi/operations/inject/_.WiFi..json
wifi/operations/inject/avm.json
wifi/operations/inject/avm_lightscan_as_bulk_data.json
wifi/operations/inject/axwifi_realtime_valuechange.json
wifi/operations/inject/environ
lc_wifi-2023.12.15.dist-info/LICENSE
lc_wifi-2023.12.15.dist-info/METADATA
lc_wifi-2023.12.15.dist-info/WHEEL
lc_wifi-2023.12.15.dist-info/entry_points.txt
lc_wifi-2023.12.15.dist-info/RECORD
