Metadata-Version: 2.1
Name: lc-wifi
Version: 2023.12.15
Summary: Low Code WiFi Processing
Home-page: http://devapps.pages.axiros.com/lc-wifi.git
License: Commercial
Author: Gunther Klessinger
Author-email: gk@axiros.com
Requires-Python: >=3.8,<4.0
Classifier: License :: Other/Proprietary License
Classifier: Programming Language :: Python :: 3
Classifier: Programming Language :: Python :: 3.8
Classifier: Programming Language :: Python :: 3.9
Classifier: Programming Language :: Python :: 3.10
Classifier: Programming Language :: Python :: 3.11
Requires-Dist: clickhouse-connect (>=0.6.22,<0.7.0)
Requires-Dist: confluent-kafka (>=1.8.2,<2.0.0)
Requires-Dist: elasticsearch (>=7.16.3,<8.0.0)
Requires-Dist: elasticsearch-dsl (>=7.4.0,<8.0.0)
Requires-Dist: lc-python (==2023.12.14)
Requires-Dist: netaddr
Requires-Dist: rich
Project-URL: Repository, https://gitlab.axiros.com/devapps/lc-wifi.git
